[
  {
    "nama_kos": "Kost Cozykost Tipe D Laweyan Surakarta",
    "jenis_kos": "Kos Putri",
    "area": "Laweyan",
    "rating": "5.0",
    "jumlah_review": "(2)",
    "total_transaksi": "3 transaksi berhasil di kos ini",
    "harga": "Rp1.400.000",
    "periode": "/bulan",
    "alamat": "Laweyan, Kota Surakarta, Surakarta",
    "fasilitas": {
      "ukuran_listrik": [
        "3 x 4 meter",
        "Tidak termasuk listrik"
      ],
      "kamar": [
        "AC",
        "Kasur",
        "Lemari / Storage"
      ],
      "kamar_mandi": [
        "K. Mandi Dalam",
        "Kloset Duduk",
        "K. Mandi Luar"
      ],
      "umum": [
        "R. Jemur"
      ],
      "parkir": [
        "Parkir Mobil",
        "Parkir Motor",
        "Parkir Sepeda"
      ]
    },
    "peraturan": [
      "Tipe ini bisa diisi maks. 1 orang/ kamar",
      "Tidak untuk pasutri",
      "Tidak boleh bawa anak",
      "Akses 24 Jam",
      "Denda kerusakan barang kos",
      "Dilarang bawa hewan",
      "Maks. 1 orang/ kamar"
    ],
    "landmarks": [
      {
        "nama": "Berseri Warmindo",
        "jarak": "689 m"
      },
      {
        "nama": "Masjid Kota Barat Surakarta",
        "jarak": "257 m"
      },
      {
        "nama": "Sekolah Tinggi Pariwisata Sahid",
        "jarak": "2.9 km"
      },
      {
        "nama": "RS Gigi dan Mulut Soelastri",
        "jarak": "341 m"
      },
      {
        "nama": "Solo Paragon Mall",
        "jarak": "138 m"
      }
    ],
    "region": "solo-kota-surakarta-jawa-tengah-indonesia",
    "url": "https://mamikos.com/room/kost-kota-surakarta-kost-putri-eksklusif-kost-cozykost-tipe-d-laweyan-surakarta-1?redirection_source=list%20kos%20result",
    "scraped_at": "2025-09-27T10:42:27.637741"
  },
  {
    "nama_kos": "Kost Cozykost Tipe C Laweyan Surakarta",
    "jenis_kos": "Kos Putri",
    "area": "Laweyan",
    "rating": "",
    "jumlah_review": "",
    "total_transaksi": "11 transaksi berhasil di kos ini",
    "harga": "Rp1.300.000",
    "periode": "/bulan",
    "alamat": "Laweyan, Kota Surakarta, Surakarta",
    "fasilitas": {
      "ukuran_listrik": [
        "3 x 3.5 meter",
        "Tidak termasuk listrik"
      ],
      "kamar": [
        "AC",
        "Kasur",
        "Lemari / Storage"
      ],
      "kamar_mandi": [
        "TV Kabel",
        "K. Mandi Dalam",
        "Kloset Duduk",
        "K. Mandi Luar"
      ],
      "umum": [
        "CCTV"
      ],
      "parkir": [
        "Parkir Mobil",
        "Parkir Motor",
        "Parkir Sepeda"
      ]
    },
    "peraturan": [
      "Tipe ini bisa diisi maks. 1 orang/ kamar",
      "Tidak untuk pasutri",
      "Tidak boleh bawa anak",
      "Akses 24 Jam",
      "Dilarang bawa hewan",
      "Maks. 1 orang/ kamar"
    ],
    "landmarks": [
      {
        "nama": "Berseri Warmindo",
        "jarak": "663 m"
      },
      {
        "nama": "Masjid Kota Barat Surakarta",
        "jarak": "290 m"
      },
      {
        "nama": "Sekolah Tinggi Pariwisata Sahid",
        "jarak": "3.0 km"
      },
      {
        "nama": "RS Gigi dan Mulut Soelastri",
        "jarak": "302 m"
      },
      {
        "nama": "Solo Paragon Mall",
        "jarak": "161 m"
      }
    ],
    "region": "solo-kota-surakarta-jawa-tengah-indonesia",
    "url": "https://mamikos.com/room/kost-kota-surakarta-kost-putri-eksklusif-kost-cozykost-tipe-c-laweyan-surakarta?redirection_source=list%20kos%20result",
    "scraped_at": "2025-09-27T10:42:41.358032"
  },
  {
    "nama_kos": "Kost Apik Pringgading Setabelan Tipe A Banjarsari Surakarta",
    "jenis_kos": "Kos Putra",
    "area": "Banjarsari",
    "rating": "4.8",
    "jumlah_review": "(46)",
    "total_transaksi": "81 transaksi berhasil di kos ini",
    "harga": "Rp522.200",
    "periode": "(Bulan pertama)",
    "alamat": "Banjarsari, Kota Surakarta, Surakarta",
    "fasilitas": {
      "ukuran_listrik": [
        "2.5 x 3 meter",
        "Termasuk listrik"
      ],
      "kamar": [
        "Kasur",
        "Lemari / Storage",
        "Bantal",
        "Cermin",
        "Jendela"
      ],
      "kamar_mandi": [
        "Kloset Jongkok",
        "K. Mandi Luar",
        "Ember mandi",
        "Shower"
      ],
      "umum": [
        "WiFi",
        "R. Tamu",
        "Penjaga Kos",
        "R. Jemur",
        "Dapur"
      ],
      "parkir": [
        "Parkir Motor",
        "Parkir Sepeda"
      ]
    },
    "peraturan": [
      "Tamu menginap dikenakan biaya",
      "Tipe ini bisa diisi maks. 2 orang/ kamar",
      "Tidak untuk pasutri",
      "Tidak boleh bawa anak",
      "Tambah biaya untuk alat elektronik",
      "Deposit",
      "Akses 24 Jam",
      "Maks. 2 orang/ kamar",
      "Dilarang merokok di kamar",
      "Tambah biaya untuk alat elektronik",
      "Lawan jenis dilarang ke kamar"
    ],
    "landmarks": [
      {
        "nama": "Dkve Warmindo",
        "jarak": "1.2 km"
      },
      {
        "nama": "Gereja Bethany Solo",
        "jarak": "424 m"
      },
      {
        "nama": "Universitas Sebelas Maret",
        "jarak": "3.2 km"
      },
      {
        "nama": "RS Umum PKU Muhammadiyah Surakarta",
        "jarak": "1.3 km"
      },
      {
        "nama": "Solo Paragon Mall",
        "jarak": "2.1 km"
      }
    ],
    "region": "solo-kota-surakarta-jawa-tengah-indonesia",
    "url": "https://mamikos.com/room/kost-surakarta-kost-putra-murah-kost-apik-pringgading-setabelan-tipe-a-banjarsari-surakarta-1?redirection_source=list%20kos%20result",
    "scraped_at": "2025-09-27T10:42:55.828369"
  },
  {
    "nama_kos": "Kost Griya Margi Anja Tegalrejo Jebres Surakarta",
    "jenis_kos": "Kos Putra",
    "area": "Jebres",
    "rating": "",
    "jumlah_review": "",
    "total_transaksi": "1 transaksi berhasil di kos ini",
    "harga": "Rp1.100.000",
    "periode": "/bulan",
    "alamat": "Jebres, Kota Surakarta, Surakarta",
    "fasilitas": {
      "ukuran_listrik": [
        "3 x 4 meter",
        "Tidak termasuk listrik"
      ],
      "kamar": [
        "AC",
        "Kasur",
        "Meja",
        "Lemari / Storage",
        "Kursi"
      ],
      "kamar_mandi": [
        "Kloset Duduk",
        "Kloset Jongkok",
        "K. Mandi Luar",
        "Wastafel",
        "Shower",
        "R. Santai"
      ],
      "umum": [
        "WiFi",
        "Kulkas",
        "R. Tamu",
        "R. Jemur"
      ],
      "parkir": [
        "Parkir Mobil",
        "Parkir Motor",
        "Parkir Sepeda"
      ]
    },
    "peraturan": [
      "Tipe ini bisa diisi maks. 1 orang/ kamar",
      "Tidak untuk pasutri",
      "Tidak boleh bawa anak"
    ],
    "landmarks": [
      {
        "nama": "Warteg Alaska",
        "jarak": "1.8 km"
      },
      {
        "nama": "Bethel Full Gospel Church Kepunton",
        "jarak": "1.2 km"
      },
      {
        "nama": "Universitas Sebelas Maret",
        "jarak": "1.6 km"
      },
      {
        "nama": "RS Umum Hermina Solo",
        "jarak": "276 m"
      }
    ],
    "region": "solo-kota-surakarta-jawa-tengah-indonesia",
    "url": "https://mamikos.com/room/kost-surakarta-kost-putra-murah-kost-griya-margi-anja-tegalrejo-jebres-surakarta?redirection_source=list%20kos%20result",
    "scraped_at": "2025-09-27T10:43:05.917413"
  },
  {
    "nama_kos": "Kost Griya Sewu Jebres Surakarta",
    "jenis_kos": "Kos Putra",
    "area": "Jebres",
    "rating": "5.0",
    "jumlah_review": "(1)",
    "total_transaksi": "9 transaksi berhasil di kos ini",
    "harga": "Rp1.500.000",
    "periode": "/bulan",
    "alamat": "",
    "fasilitas": {
      "ukuran_listrik": [
        "3 x 4 meter",
        "Tidak termasuk listrik"
      ],
      "kamar": [
        "AC",
        "Kasur",
        "Meja Rias",
        "Lemari / Storage",
        "Bantal"
      ],
      "kamar_mandi": [
        "K. Mandi Dalam",
        "Kloset Duduk",
        "Shower",
        "Air panas",
        "Taman"
      ],
      "umum": [
        "Penjaga Kos",
        "R. Jemur",
        "Dapur"
      ],
      "parkir": [
        "Parkir Motor"
      ]
    },
    "peraturan": [
      "Tipe ini bisa diisi maks. 1 orang/ kamar",
      "Tidak untuk pasutri",
      "Tidak boleh bawa anak",
      "Akses 24 Jam",
      "Dilarang bawa hewan",
      "Khusus karyawan",
      "Kamar hanya bagi penyewa",
      "Tamu dilarang menginap"
    ],
    "landmarks": [
      {
        "nama": "Warteg Alaska",
        "jarak": "2.7 km"
      },
      {
        "nama": "Bethel Full Gospel Church Kepunton",
        "jarak": "1.5 km"
      },
      {
        "nama": "Universitas Sebelas Maret",
        "jarak": "2.0 km"
      },
      {
        "nama": "RS Umum Hermina Solo",
        "jarak": "1.2 km"
      }
    ],
    "region": "solo-kota-surakarta-jawa-tengah-indonesia",
    "url": "https://mamikos.com/room/kost-kota-surakarta-kost-campur-eksklusif-kost-griya-sewu-jebres-surakarta?redirection_source=list%20kos%20result",
    "scraped_at": "2025-09-27T10:43:16.778901"
  },
  {
    "nama_kos": "Kost Griya Bawono Tipe Sedang Jebres Surakarta",
    "jenis_kos": "Kos Campur",
    "area": "Kecamatan Jebres",
    "rating": "",
    "jumlah_review": "",
    "total_transaksi": "3 transaksi berhasil di kos ini",
    "harga": "Rp2.000.000",
    "periode": "/bulan",
    "alamat": "Kecamatan Jebres, Kota Surakarta, Surakarta",
    "fasilitas": {
      "ukuran_listrik": [
        "3 x 4 meter",
        "Tidak termasuk listrik"
      ],
      "kamar": [
        "AC",
        "Kasur",
        "Meja",
        "Meja Rias",
        "TV"
      ],
      "kamar_mandi": [
        "K. Mandi Dalam",
        "Kloset Duduk",
        "Wastafel",
        "Shower",
        "Air panas",
        "R. Santai"
      ],
      "umum": [
        "WiFi",
        "Penjaga Kos",
        "R. Tamu",
        "R. Jemur"
      ],
      "parkir": [
        "Parkir Mobil",
        "Parkir Motor",
        "Parkir Sepeda"
      ]
    },
    "peraturan": [
      "Tamu menginap dikenakan biaya",
      "Tipe ini bisa diisi maks. 2 orang/ kamar",
      "Boleh pasutri",
      "Boleh bawa anak",
      "Denda keterlambatan",
      "Ada jam malam untuk tamu",
      "Akses 24 Jam",
      "Boleh pasutri",
      "Boleh bawa anak",
      "Dilarang merokok di kamar"
    ],
    "landmarks": [
      {
        "nama": "Rumah Makan Pak Die Solo Balapan",
        "jarak": "935 m"
      },
      {
        "nama": "Bethel Full Gospel Church Kepunton",
        "jarak": "289 m"
      },
      {
        "nama": "Universitas Sebelas Maret",
        "jarak": "3.0 km"
      },
      {
        "nama": "RS Umum Triharsi",
        "jarak": "728 m"
      },
      {
        "nama": "Solo Paragon Mall",
        "jarak": "2.2 km"
      }
    ],
    "region": "solo-kota-surakarta-jawa-tengah-indonesia",
    "url": "https://mamikos.com/room/kost-kota-surakarta-kost-campur-eksklusif-kost-griya-bawono-tipe-sedang-jebres-surakarta?redirection_source=list%20kos%20result",
    "scraped_at": "2025-09-27T10:43:29.298939"
  },
  {
    "nama_kos": "Kost Mayangsari Serengan Surakarta",
    "jenis_kos": "Kos Putra",
    "area": "Serengan",
    "rating": "4.8",
    "jumlah_review": "(4)",
    "total_transaksi": "19 transaksi berhasil di kos ini",
    "harga": "Rp530.000",
    "periode": "/bulan",
    "alamat": "Serengan, Surakarta, Surakarta",
    "fasilitas": {
      "ukuran_listrik": [
        "3 x 2 meter",
        "Termasuk listrik"
      ],
      "kamar": [
        "Kasur",
        "Lemari / Storage",
        "Kipas Angin",
        "Bantal"
      ],
      "kamar_mandi": [
        "Kloset Jongkok",
        "K. Mandi Luar",
        "Wastafel",
        "Ember mandi"
      ],
      "umum": [
        "WiFi",
        "R. Cuci",
        "R. Tamu",
        "Penjaga Kos",
        "Jemuran"
      ],
      "parkir": [
        "Parkir Motor",
        "Parkir Sepeda"
      ]
    },
    "peraturan": [
      "Tipe ini bisa diisi maks. 1 orang/ kamar",
      "Tidak untuk pasutri",
      "Tidak boleh bawa anak",
      "Ada jam malam untuk tamu",
      "Akses 24 Jam",
      "Dilarang bawa hewan",
      "Kamar hanya bagi penyewa",
      "Khusus karyawan"
    ],
    "landmarks": [
      {
        "nama": "Berseri Warmindo",
        "jarak": "2.5 km"
      },
      {
        "nama": "Masjid At Taqwa Grobagan Danukusuman Solo",
        "jarak": "321 m"
      },
      {
        "nama": "Akademi Analis Kesehatan Nasional Surakarta",
        "jarak": "340 m"
      },
      {
        "nama": "The Park Mall Solo Baru, Grogol",
        "jarak": "1.5 km"
      }
    ],
    "region": "solo-kota-surakarta-jawa-tengah-indonesia",
    "url": "https://mamikos.com/room/kost-surakarta-kost-putra-murah-kost-mayangsari-serengan-surakarta?redirection_source=list%20kos%20result",
    "scraped_at": "2025-09-27T10:43:38.961341"
  },
  {
    "nama_kos": "Kost Singgahsini Parkit 3 Tipe A Banjarsari Surakarta",
    "jenis_kos": "Kos Putri",
    "area": "Banjarsari",
    "rating": "",
    "jumlah_review": "",
    "total_transaksi": "",
    "harga": "Rp1.320.000",
    "periode": "(Bulan pertama)",
    "alamat": "Banjarsari, Kota Surakarta, Surakarta",
    "fasilitas": {
      "ukuran_listrik": [
        "3 x 4 meter",
        "Tidak termasuk listrik"
      ],
      "kamar": [
        "AC",
        "Kasur",
        "Meja",
        "Lemari / Storage",
        "Kursi"
      ],
      "kamar_mandi": [
        "K. Mandi Dalam",
        "Kloset Duduk",
        "Wastafel",
        "Ember mandi",
        "Shower"
      ],
      "umum": [
        "WiFi",
        "R. Cuci",
        "R. Tamu",
        "Penjaga Kos",
        "R. Jemur"
      ],
      "parkir": [
        "Parkir Motor & Sepeda"
      ]
    },
    "peraturan": [
      "Tamu boleh menginap",
      "Tamu menginap dikenakan biaya",
      "Tipe ini bisa diisi maks. 1 orang/ kamar",
      "Tidak untuk pasutri",
      "Tidak boleh bawa anak",
      "Deposit",
      "Tidak boleh bawa anak",
      "Dilarang merokok di kamar",
      "Tidak untuk pasutri",
      "Lawan jenis dilarang ke kamar",
      "Tamu boleh menginap"
    ],
    "landmarks": [
      {
        "nama": "Warteg Bolodewe",
        "jarak": "195 m"
      },
      {
        "nama": "Masjid Al Wustho Mangkunegaran",
        "jarak": "1.5 km"
      },
      {
        "nama": "Universitas Tunas Pembangunan Surakarta (UTP)",
        "jarak": "753 m"
      },
      {
        "nama": "RS Gigi dan Mulut Soelastri",
        "jarak": "911 m"
      },
      {
        "nama": "Solo Paragon Mall",
        "jarak": "503 m"
      }
    ],
    "region": "solo-kota-surakarta-jawa-tengah-indonesia",
    "url": "https://mamikos.com/room/kost-kota-surakarta-kost-putri-eksklusif-kost-singgahsini-parkit-3-tipe-a-banjarsari-surakarta-2?redirection_source=list%20kos%20result",
    "scraped_at": "2025-09-27T10:43:51.882045"
  },
  {
    "nama_kos": "Kost Ekslusif Griya Syariah Sofia Tipe D5 Banjarsari Surakarta",
    "jenis_kos": "Kos Putri",
    "area": "Kecamatan Banjarsari",
    "rating": "5.0",
    "jumlah_review": "(1)",
    "total_transaksi": "",
    "harga": "Rp1.250.000",
    "periode": "/bulan",
    "alamat": "Kecamatan Banjarsari, Kota Surakarta, Surakarta",
    "fasilitas": {
      "ukuran_listrik": [
        "3 x 4 meter",
        "Tidak termasuk listrik"
      ],
      "kamar": [
        "AC",
        "Kasur",
        "Meja",
        "Lemari / Storage",
        "Ventilasi"
      ],
      "kamar_mandi": [
        "K. Mandi Dalam",
        "Kloset Duduk",
        "Ember mandi",
        "Shower",
        "R. Santai"
      ],
      "umum": [
        "WiFi",
        "Kulkas",
        "R. Jemur",
        "Dapur"
      ],
      "parkir": [
        "Parkir Motor",
        "Parkir Sepeda",
        "Parkir Motor & Sepeda"
      ]
    },
    "peraturan": [
      "Tamu menginap dikenakan biaya",
      "Tipe ini bisa diisi maks. 1 orang/ kamar",
      "Tidak untuk pasutri",
      "Tidak boleh bawa anak",
      "Deposit",
      "Ada jam malam untuk tamu",
      "Akses 24 Jam",
      "Check-in pukul 14:00-21:00 (sewa harian)",
      "Check-out maks. pukul 12:00 (sewa harian)",
      "Denda kerusakan barang kos"
    ],
    "landmarks": [
      {
        "nama": "Rumah Makan Pak Die Solo Balapan",
        "jarak": "559 m"
      },
      {
        "nama": "Masjid Al Wustho Mangkunegaran",
        "jarak": "655 m"
      },
      {
        "nama": "Universitas Tunas Pembangunan Surakarta (UTP)",
        "jarak": "1.3 km"
      },
      {
        "nama": "RS Umum Triharsi",
        "jarak": "870 m"
      },
      {
        "nama": "Solo Paragon Mall",
        "jarak": "908 m"
      }
    ],
    "region": "solo-kota-surakarta-jawa-tengah-indonesia",
    "url": "https://mamikos.com/room/kost-kota-surakarta-kost-putri-eksklusif-kost-ekslusif-griya-syariah-sofia-tipe-d5-banjarsari-surakarta-2?redirection_source=list%20kos%20result",
    "scraped_at": "2025-09-27T10:44:06.469315"
  },
  {
    "nama_kos": "Kost Safir Executive Slamet Riyadi Tipe A Laweyan Surakarta",
    "jenis_kos": "Kos Putra",
    "area": "Kecamatan Laweyan",
    "rating": "",
    "jumlah_review": "",
    "total_transaksi": "",
    "harga": "Rp1.600.000",
    "periode": "/bulan",
    "alamat": "Kecamatan Laweyan, Kota Surakarta, Surakarta",
    "fasilitas": {
      "ukuran_listrik": [
        "3 x 4 meter",
        "Tidak termasuk listrik"
      ],
      "kamar": [
        "AC",
        "Kasur",
        "Meja",
        "Lemari / Storage",
        "Ventilasi"
      ],
      "kamar_mandi": [
        "K. Mandi Dalam",
        "Kloset Duduk",
        "Shower",
        "Air panas"
      ],
      "umum": [
        "WiFi",
        "Kulkas",
        "R. Cuci",
        "Mesin Cuci",
        "Penjaga Kos"
      ],
      "parkir": [
        "Parkir Mobil",
        "Parkir Motor"
      ]
    },
    "peraturan": [
      "Tipe ini bisa diisi maks. 1 orang/ kamar",
      "Tidak untuk pasutri",
      "Tidak boleh bawa anak",
      "Deposit",
      "Denda keterlambatan",
      "Ada jam malam untuk tamu",
      "Akses 24 Jam",
      "Denda kerusakan barang kos",
      "Dilarang bawa hewan",
      "Kamar hanya bagi penyewa"
    ],
    "landmarks": [
      {
        "nama": "Rumah Makan Pak Die Solo Balapan",
        "jarak": "1.2 km"
      },
      {
        "nama": "Masjid Al Wustho Mangkunegaran",
        "jarak": "590 m"
      },
      {
        "nama": "Bank Mandiri Solo Baru Raya",
        "jarak": "3.4 km"
      },
      {
        "nama": "Universitas Tunas Pembangunan Surakarta (UTP)",
        "jarak": "1.9 km"
      },
      {
        "nama": "RS Umum Triharsi",
        "jarak": "1.4 km"
      },
      {
        "nama": "Solo Paragon Mall",
        "jarak": "921 m"
      }
    ],
    "region": "solo-kota-surakarta-jawa-tengah-indonesia",
    "url": "https://mamikos.com/room/kost-kota-surakarta-kost-putra-eksklusif-kost-safir-executive-slamet-riyadi-tipe-a-laweyan-surakarta?redirection_source=list%20kos%20result",
    "scraped_at": "2025-09-27T10:44:17.576268"
  },
  {
    "nama_kos": "Kost Annisa Pasar Kliwon Surakarta",
    "jenis_kos": "Kos Putri",
    "area": "Pasar Kliwon",
    "rating": "",
    "jumlah_review": "",
    "total_transaksi": "",
    "harga": "Rp550.000",
    "periode": "/bulan",
    "alamat": "Pasar Kliwon, Kota Surakarta, Surakarta",
    "fasilitas": {
      "ukuran_listrik": [
        "3 x 3 meter",
        "Tidak termasuk listrik"
      ],
      "kamar": [
        "Kasur",
        "Meja",
        "Lemari / Storage",
        "Ventilasi",
        "Bantal"
      ],
      "kamar_mandi": [
        "K. Mandi Dalam",
        "Kloset Jongkok",
        "Ember mandi"
      ],
      "umum": [
        "WiFi",
        "Kulkas",
        "R. Cuci",
        "Penjaga Kos",
        "R. Jemur"
      ],
      "parkir": [
        "Parkir Motor & Sepeda"
      ]
    },
    "peraturan": [
      "Tipe ini bisa diisi maks. 2 orang/ kamar",
      "Tidak untuk pasutri",
      "Tidak boleh bawa anak",
      "Akses 24 Jam",
      "Denda kerusakan barang kos",
      "Dilarang bawa hewan",
      "Dilarang merokok di kamar",
      "Kamar hanya bagi penyewa"
    ],
    "landmarks": [
      {
        "nama": "Warmindo Susubini",
        "jarak": "1.7 km"
      },
      {
        "nama": "Masjid Al - Mukmin Surakarta",
        "jarak": "1.1 km"
      },
      {
        "nama": "BCA KCU Solo Baru",
        "jarak": "1.8 km"
      },
      {
        "nama": "Akademi Analis Kesehatan Nasional Surakarta",
        "jarak": "1.7 km"
      },
      {
        "nama": "RSUP Surakarta",
        "jarak": "126 m"
      },
      {
        "nama": "The Park Mall Solo Baru, Grogol",
        "jarak": "1.9 km"
      }
    ],
    "region": "solo-kota-surakarta-jawa-tengah-indonesia",
    "url": "https://mamikos.com/room/kost-kota-surakarta-kost-putri-murah-kost-annisa-pasar-kliwon-surakarta-2?redirection_source=list%20kos%20result",
    "scraped_at": "2025-09-27T10:44:28.273773"
  },
  {
    "nama_kos": "Kost Singgahsini Parkit 3 Tipe B Banjarsari Surakarta",
    "jenis_kos": "Kos Putri",
    "area": "Banjarsari",
    "rating": "",
    "jumlah_review": "",
    "total_transaksi": "",
    "harga": "Rp1.188.000",
    "periode": "(Bulan pertama)",
    "alamat": "Banjarsari, Kota Surakarta, Surakarta",
    "fasilitas": {
      "ukuran_listrik": [
        "3.5 x 3.5 meter",
        "Tidak termasuk listrik"
      ],
      "kamar": [
        "AC",
        "Kasur",
        "Meja",
        "Lemari / Storage",
        "Kursi"
      ],
      "kamar_mandi": [
        "K. Mandi Dalam",
        "Kloset Duduk",
        "Wastafel",
        "Ember mandi",
        "Shower"
      ],
      "umum": [
        "WiFi",
        "R. Cuci",
        "R. Tamu",
        "Penjaga Kos",
        "R. Jemur"
      ],
      "parkir": [
        "Parkir Motor & Sepeda"
      ]
    },
    "peraturan": [
      "Tamu boleh menginap",
      "Tamu menginap dikenakan biaya",
      "Tipe ini bisa diisi maks. 1 orang/ kamar",
      "Tidak untuk pasutri",
      "Tidak boleh bawa anak",
      "Deposit",
      "Tidak boleh bawa anak",
      "Dilarang merokok di kamar",
      "Tidak untuk pasutri",
      "Lawan jenis dilarang ke kamar",
      "Tamu boleh menginap"
    ],
    "landmarks": [
      {
        "nama": "Warteg Bolodewe",
        "jarak": "195 m"
      },
      {
        "nama": "Masjid Al Wustho Mangkunegaran",
        "jarak": "1.5 km"
      },
      {
        "nama": "Universitas Tunas Pembangunan Surakarta (UTP)",
        "jarak": "753 m"
      },
      {
        "nama": "RS Gigi dan Mulut Soelastri",
        "jarak": "911 m"
      },
      {
        "nama": "Solo Paragon Mall",
        "jarak": "503 m"
      }
    ],
    "region": "solo-kota-surakarta-jawa-tengah-indonesia",
    "url": "https://mamikos.com/room/kost-kota-surakarta-kost-putri-eksklusif-kost-singgahsini-parkit-3-tipe-b-banjarsari-surakarta-2?redirection_source=list%20kos%20result",
    "scraped_at": "2025-09-27T10:44:38.468105"
  },
  {
    "nama_kos": "Kost Singgahsini Parkit 3 Tipe C Banjarsari Surakarta",
    "jenis_kos": "Kos Putri",
    "area": "Banjarsari",
    "rating": "",
    "jumlah_review": "",
    "total_transaksi": "",
    "harga": "Rp1.100.000",
    "periode": "(Bulan pertama)",
    "alamat": "Banjarsari, Kota Surakarta, Surakarta",
    "fasilitas": {
      "ukuran_listrik": [
        "3 x 3.5 meter",
        "Tidak termasuk listrik"
      ],
      "kamar": [
        "AC",
        "Kasur",
        "Meja",
        "Lemari / Storage",
        "Kursi"
      ],
      "kamar_mandi": [
        "K. Mandi Dalam",
        "Kloset Duduk",
        "Ember mandi",
        "Shower"
      ],
      "umum": [
        "WiFi",
        "R. Cuci",
        "R. Tamu",
        "Penjaga Kos",
        "R. Jemur"
      ],
      "parkir": [
        "Parkir Motor & Sepeda"
      ]
    },
    "peraturan": [
      "Tamu boleh menginap",
      "Tamu menginap dikenakan biaya",
      "Tipe ini bisa diisi maks. 1 orang/ kamar",
      "Tidak untuk pasutri",
      "Tidak boleh bawa anak",
      "Deposit",
      "Tidak boleh bawa anak",
      "Dilarang merokok di kamar",
      "Tidak untuk pasutri",
      "Lawan jenis dilarang ke kamar",
      "Tamu boleh menginap"
    ],
    "landmarks": [
      {
        "nama": "Warteg Bolodewe",
        "jarak": "195 m"
      },
      {
        "nama": "Masjid Al Wustho Mangkunegaran",
        "jarak": "1.5 km"
      },
      {
        "nama": "Universitas Tunas Pembangunan Surakarta (UTP)",
        "jarak": "753 m"
      },
      {
        "nama": "RS Gigi dan Mulut Soelastri",
        "jarak": "911 m"
      },
      {
        "nama": "Solo Paragon Mall",
        "jarak": "503 m"
      }
    ],
    "region": "solo-kota-surakarta-jawa-tengah-indonesia",
    "url": "https://mamikos.com/room/kost-kota-surakarta-kost-putri-eksklusif-kost-singgahsini-parkit-3-tipe-c-banjarsari-surakarta-2?redirection_source=list%20kos%20result",
    "scraped_at": "2025-09-27T10:44:49.511338"
  },
  {
    "nama_kos": "Kost Titin Pasar Kliwon Surakarta",
    "jenis_kos": "Kos Campur",
    "area": "Pasar Kliwon",
    "rating": "",
    "jumlah_review": "",
    "total_transaksi": "",
    "harga": "Rp650.000",
    "periode": "/bulan",
    "alamat": "Pasar Kliwon, Kota Surakarta, Surakarta",
    "fasilitas": {
      "ukuran_listrik": [
        "3 x 4 meter",
        "Tidak termasuk listrik"
      ],
      "kamar": [
        "Jendela"
      ],
      "kamar_mandi": [
        "K. Mandi Dalam",
        "Kloset Duduk"
      ],
      "umum": [
        "R. Cuci",
        "Penjaga Kos",
        "Mushola",
        "R. Jemur",
        "Jemuran"
      ],
      "parkir": [
        "Parkir Motor",
        "Parkir Sepeda",
        "Parkir Motor & Sepeda"
      ]
    },
    "peraturan": [
      "Tamu boleh menginap",
      "Tipe ini bisa diisi maks. 1 orang/ kamar",
      "Boleh pasutri",
      "Boleh bawa anak",
      "Denda keterlambatan",
      "Boleh bawa anak",
      "Boleh pasutri",
      "Dilarang bawa hewan",
      "Kriteria umum",
      "Tamu bebas berkunjung"
    ],
    "landmarks": [
      {
        "nama": "Berseri Warmindo",
        "jarak": "3.2 km"
      },
      {
        "nama": "Masjid Ar Riyadh Solo",
        "jarak": "651 m"
      },
      {
        "nama": "RSU Umum Daerah Bung Karno Kota Surakarta",
        "jarak": "493 m"
      },
      {
        "nama": "The Park Mall Solo Baru, Grogol",
        "jarak": "2.0 km"
      }
    ],
    "region": "solo-kota-surakarta-jawa-tengah-indonesia",
    "url": "https://mamikos.com/room/kost-kota-surakarta-kost-campur-murah-kost-titin-pasar-kliwon-surakarta-2?redirection_source=list%20kos%20result",
    "scraped_at": "2025-09-27T10:44:58.407023"
  },
  {
    "nama_kos": "Kost Olive Paragon Mall Tipe B1 Banjarsari Surakarta",
    "jenis_kos": "Kos Putri",
    "area": "Banjarsari",
    "rating": "",
    "jumlah_review": "",
    "total_transaksi": "",
    "harga": "Rp700.000",
    "periode": "/bulan",
    "alamat": "Banjarsari, Kota Surakarta, Surakarta",
    "fasilitas": {
      "ukuran_listrik": [
        "5 x 6 meter",
        "Termasuk listrik"
      ],
      "kamar": [
        "Kasur",
        "Meja",
        "Lemari / Storage",
        "Kursi",
        "Bantal"
      ],
      "kamar_mandi": [
        "Kloset Duduk",
        "K. Mandi Luar",
        "Shower"
      ],
      "umum": [
        "WiFi",
        "Kulkas",
        "R. Tamu",
        "Penjaga Kos",
        "R. Jemur"
      ],
      "parkir": [
        "Parkir Mobil",
        "Parkir Motor",
        "Parkir Sepeda"
      ]
    },
    "peraturan": [
      "Tamu menginap dikenakan biaya",
      "Tipe ini bisa diisi maks. 2 orang/ kamar",
      "Tidak untuk pasutri",
      "Tidak boleh bawa anak",
      "Deposit",
      "Ada jam malam",
      "Ada jam malam untuk tamu",
      "Akses 24 Jam",
      "Denda kerusakan barang kos",
      "Dilarang bawa hewan"
    ],
    "landmarks": [
      {
        "nama": "Warteg Bolodewe",
        "jarak": "538 m"
      },
      {
        "nama": "Masjid Al Wustho Mangkunegaran",
        "jarak": "1.3 km"
      },
      {
        "nama": "Universitas Tunas Pembangunan Surakarta (UTP)",
        "jarak": "1.1 km"
      },
      {
        "nama": "RS Gigi dan Mulut Soelastri",
        "jarak": "659 m"
      },
      {
        "nama": "Solo Paragon Mall",
        "jarak": "198 m"
      }
    ],
    "region": "solo-kota-surakarta-jawa-tengah-indonesia",
    "url": "https://mamikos.com/room/kost-kota-surakarta-kost-putri-murah-kost-olive-paragon-mall-tipe-b1-banjarsari-surakarta-2?redirection_source=list%20kos%20result",
    "scraped_at": "2025-09-27T10:45:08.524514"
  },
  {
    "nama_kos": "Kost Berkat Abadi Tipe A Jebres Surakarta",
    "jenis_kos": "Kos Putri",
    "area": "Jebres",
    "rating": "",
    "jumlah_review": "",
    "total_transaksi": "3 transaksi berhasil di kos ini",
    "harga": "Rp450.000",
    "periode": "/bulan",
    "alamat": "Jebres, Kota Surakarta, Surakarta",
    "fasilitas": {
      "ukuran_listrik": [
        "2 x 3 meter",
        "Tidak termasuk listrik"
      ],
      "kamar": [
        "Kasur",
        "Meja",
        "Lemari / Storage",
        "Ventilasi",
        "Bantal"
      ],
      "kamar_mandi": [
        "Kloset Duduk",
        "Kloset Jongkok",
        "K. Mandi Luar",
        "Ember mandi",
        "R. Santai"
      ],
      "umum": [
        "R. Cuci",
        "Laundry",
        "R. Tamu",
        "R. Jemur"
      ],
      "parkir": [
        "Parkir Motor",
        "Parkir Sepeda"
      ]
    },
    "peraturan": [
      "Tamu menginap dikenakan biaya",
      "Tipe ini bisa diisi maks. 2 orang/ kamar",
      "Tidak untuk pasutri",
      "Tidak boleh bawa anak",
      "Tambah biaya untuk alat elektronik",
      "Ada jam malam untuk tamu",
      "Akses 24 Jam",
      "Dilarang bawa hewan",
      "Dilarang merokok di kamar",
      "Kamar hanya bagi penyewa"
    ],
    "landmarks": [
      {
        "nama": "Dkve Warmindo",
        "jarak": "2.0 km"
      },
      {
        "nama": "Bethel Full Gospel Church Kepunton",
        "jarak": "687 m"
      },
      {
        "nama": "Universitas Sebelas Maret",
        "jarak": "2.1 km"
      },
      {
        "nama": "RS Jiwa Daerah Surakarta",
        "jarak": "3.0 km"
      },
      {
        "nama": "Solo Paragon Mall",
        "jarak": "3.1 km"
      }
    ],
    "region": "solo-kota-surakarta-jawa-tengah-indonesia",
    "url": "https://mamikos.com/room/kost-kota-surakarta-kost-putri-murah-kost-berkat-abadi-tipe-a-jebres-surakarta?redirection_source=list%20kos%20result",
    "scraped_at": "2025-09-27T10:45:19.287688"
  },
  {
    "nama_kos": "Kost Dalimo Tipe A Serengan Surakarta",
    "jenis_kos": "Kos Putri",
    "area": "Serengan",
    "rating": "",
    "jumlah_review": "",
    "total_transaksi": "3 transaksi berhasil di kos ini",
    "harga": "Rp650.000",
    "periode": "/bulan",
    "alamat": "Serengan, Kota Surakarta, Surakarta",
    "fasilitas": {
      "ukuran_listrik": [
        "3 x 4 meter",
        "Tidak termasuk listrik"
      ],
      "kamar": [
        "Kasur",
        "Lemari / Storage",
        "Cermin",
        "Jendela"
      ],
      "kamar_mandi": [
        "K. Mandi Dalam",
        "Kloset Jongkok",
        "Ember mandi"
      ],
      "umum": [
        "WiFi",
        "R. Cuci",
        "Kulkas",
        "Penjaga Kos",
        "R. Jemur"
      ],
      "parkir": [
        "Parkir Motor",
        "Parkir Sepeda"
      ]
    },
    "peraturan": [
      "Tipe ini bisa diisi maks. 1 orang/ kamar",
      "Tidak untuk pasutri",
      "Tidak boleh bawa anak",
      "Maks. 1 orang/ kamar"
    ],
    "landmarks": [
      {
        "nama": "Berseri Warmindo",
        "jarak": "1.3 km"
      },
      {
        "nama": "Masjid Raya Fatimah",
        "jarak": "640 m"
      },
      {
        "nama": "Akademi Analis Kesehatan Nasional Surakarta",
        "jarak": "1.2 km"
      },
      {
        "nama": "Solo Paragon Mall",
        "jarak": "1.7 km"
      }
    ],
    "region": "solo-kota-surakarta-jawa-tengah-indonesia",
    "url": "https://mamikos.com/room/kost-surakarta-kost-putri-murah-kost-muslimah-dalimo-serengan-surakarta?redirection_source=list%20kos%20result",
    "scraped_at": "2025-09-27T10:45:29.050738"
  },
  {
    "nama_kos": "Kost Bu Hadi Pasar Legi Banjarsari Surakarta",
    "jenis_kos": "Kos Putri",
    "area": "Banjarsari",
    "rating": "",
    "jumlah_review": "",
    "total_transaksi": "",
    "harga": "Rp500.000",
    "periode": "/bulan",
    "alamat": "Banjarsari, Surakarta, Surakarta",
    "fasilitas": {
      "ukuran_listrik": [
        "4 x 4 meter",
        "Tidak termasuk listrik"
      ],
      "kamar": [
        "Kasur",
        "Meja",
        "Lemari / Storage",
        "Ventilasi",
        "Bantal"
      ],
      "kamar_mandi": [
        "Kloset Jongkok",
        "K. Mandi Luar",
        "Bak mandi",
        "R. Santai"
      ],
      "umum": [
        "R. Cuci",
        "R. Tamu",
        "R. Jemur",
        "Dapur"
      ],
      "parkir": [
        "Parkir Motor",
        "Parkir Sepeda"
      ]
    },
    "peraturan": [
      "Tipe ini bisa diisi maks. 3 orang/ kamar",
      "Tidak untuk pasutri",
      "Tidak boleh bawa anak",
      "Kriteria umum",
      "Tidak untuk pasutri",
      "Maks. 3 orang/ kamar",
      "Ada jam malam"
    ],
    "landmarks": [
      {
        "nama": "Rumah Makan Pak Die Solo Balapan",
        "jarak": "472 m"
      },
      {
        "nama": "Gereja Bethany Solo",
        "jarak": "211 m"
      },
      {
        "nama": "Sekolah Tinggi Ilmu Ekonomi Adi Unggul Bhirawa",
        "jarak": "1.7 km"
      },
      {
        "nama": "RS Umum PKU Muhammadiyah Surakarta",
        "jarak": "864 m"
      },
      {
        "nama": "Solo Paragon Mall",
        "jarak": "1.5 km"
      }
    ],
    "region": "solo-kota-surakarta-jawa-tengah-indonesia",
    "url": "https://mamikos.com/room/kost-surakarta-kost-putri-murah-kost-bu-hadi-pasar-legi-banjarsari-surakarta-2?redirection_source=list%20kos%20result",
    "scraped_at": "2025-09-27T10:45:38.658943"
  },
  {
    "nama_kos": "Kost Ragil 3 Tipe A Grogol Sukoharjo",
    "jenis_kos": "Kos Putri",
    "area": "Kecamatan Grogol",
    "rating": "",
    "jumlah_review": "",
    "total_transaksi": "7 transaksi berhasil di kos ini",
    "harga": "Rp600.000",
    "periode": "/bulan",
    "alamat": "Kecamatan Grogol, Kabupaten Sukoharjo, Sukoharjo",
    "fasilitas": {
      "ukuran_listrik": [
        "3 x 4 meter",
        "Termasuk listrik"
      ],
      "kamar": [
        "Kasur",
        "Lemari / Storage",
        "Bantal",
        "Jendela",
        "Kipas Angin"
      ],
      "kamar_mandi": [
        "K. Mandi Dalam",
        "Kloset Jongkok",
        "Ember mandi",
        "R. Santai"
      ],
      "umum": [
        "WiFi",
        "Kulkas",
        "R. Tamu",
        "R. Jemur"
      ],
      "parkir": [
        "Parkir Motor",
        "Parkir Sepeda"
      ]
    },
    "peraturan": [
      "Tamu menginap dikenakan biaya",
      "Tipe ini bisa diisi maks. 2 orang/ kamar",
      "Tidak untuk pasutri",
      "Tidak boleh bawa anak",
      "Tambah biaya untuk alat elektronik",
      "Ada jam malam untuk tamu",
      "Akses 24 Jam",
      "Denda kerusakan barang kos",
      "Dilarang merokok di kamar",
      "Harga termasuk listrik (sewa harian)"
    ],
    "landmarks": [
      {
        "nama": "2Susu Cafe",
        "jarak": "2.3 km"
      },
      {
        "nama": "Masjid Al - Mukmin Surakarta",
        "jarak": "1.8 km"
      },
      {
        "nama": "Bank Mandiri Solo Baru Raya",
        "jarak": "725 m"
      },
      {
        "nama": "Akademi Analis Kesehatan Nasional Surakarta",
        "jarak": "1.4 km"
      },
      {
        "nama": "RS Umum Dr. Oen Sawit",
        "jarak": "1.8 km"
      },
      {
        "nama": "Hartono Mall Solo, Grogol",
        "jarak": "921 m"
      }
    ],
    "region": "solo-kota-surakarta-jawa-tengah-indonesia",
    "url": "https://mamikos.com/room/kost-kabupaten-sukoharjo-kost-putri-murah-kost-ragil-3-tipe-a-grogol-sukoharjo?redirection_source=list%20kos%20result",
    "scraped_at": "2025-09-27T10:45:47.348769"
  },
  {
    "nama_kos": "Kost Truntun Grogol Sukoharjo",
    "jenis_kos": "Kos Putri",
    "area": "Kecamatan Grogol",
    "rating": "",
    "jumlah_review": "",
    "total_transaksi": "",
    "harga": "Rp550.000",
    "periode": "/bulan",
    "alamat": "Kecamatan Grogol, Kabupaten Sukoharjo, Sukoharjo",
    "fasilitas": {
      "ukuran_listrik": [
        "3 x 3 meter",
        "Tidak termasuk listrik"
      ],
      "kamar": [
        "Kasur",
        "Lemari / Storage",
        "Ventilasi",
        "Bantal",
        "Guling"
      ],
      "kamar_mandi": [
        "Kloset Duduk",
        "K. Mandi Luar",
        "Ember mandi",
        "R. Makan",
        "R. Santai"
      ],
      "umum": [
        "WiFi",
        "R. Cuci",
        "R. Jemur"
      ],
      "parkir": [
        "Parkir Motor",
        "Parkir Motor & Sepeda"
      ]
    },
    "peraturan": [
      "Tipe ini bisa diisi maks. 1 orang/ kamar",
      "Tidak untuk pasutri",
      "Tidak boleh bawa anak",
      "Denda keterlambatan",
      "Ada jam malam",
      "Ada jam malam untuk tamu",
      "Denda kerusakan barang kos",
      "Dilarang bawa hewan",
      "Dilarang merokok di kamar"
    ],
    "landmarks": [
      {
        "nama": "Rumah Makan Lestari Murah",
        "jarak": "2.5 km"
      },
      {
        "nama": "Gereja GUPDI KWARASAN",
        "jarak": "1.6 km"
      },
      {
        "nama": "Bank Mandiri Solo Baru Raya",
        "jarak": "2.3 km"
      },
      {
        "nama": "Universitas Tunas Pembangunan Surakarta (UTP)",
        "jarak": "3.1 km"
      },
      {
        "nama": "RS Umum Triharsi",
        "jarak": "3.2 km"
      },
      {
        "nama": "Solo Paragon Mall",
        "jarak": "1.9 km"
      }
    ],
    "region": "solo-kota-surakarta-jawa-tengah-indonesia",
    "url": "https://mamikos.com/room/kost-kabupaten-sukoharjo-kost-putri-murah-kost-truntun-grogol-sukoharjo-2?redirection_source=list%20kos%20result",
    "scraped_at": "2025-09-27T10:45:57.204847"
  },
  {
    "nama_kos": "Kost Ndalem Mitrosuwarnan Tipe A Jebres Surakarta",
    "jenis_kos": "Kos Putri",
    "area": "Kecamatan Jebres",
    "rating": "4.4",
    "jumlah_review": "(2)",
    "total_transaksi": "8 transaksi berhasil di kos ini",
    "harga": "Rp600.000",
    "periode": "/bulan",
    "alamat": "Kecamatan Jebres, Kota Surakarta, Surakarta",
    "fasilitas": {
      "ukuran_listrik": [
        "3 x 4 meter",
        "Termasuk listrik"
      ],
      "kamar": [
        "Kasur",
        "Meja",
        "Lemari / Storage",
        "Ventilasi",
        "Bantal"
      ],
      "kamar_mandi": [
        "K. Mandi Dalam",
        "Kloset Jongkok",
        "Ember mandi",
        "Bak mandi",
        "R. Santai"
      ],
      "umum": [
        "WiFi",
        "Penjaga Kos",
        "R. Tamu",
        "R. Jemur"
      ],
      "parkir": [
        "Parkir Mobil",
        "Parkir Motor",
        "Parkir Sepeda"
      ]
    },
    "peraturan": [
      "Tipe ini bisa diisi maks. 1 orang/ kamar",
      "Tidak untuk pasutri",
      "Tidak boleh bawa anak",
      "Ada jam malam untuk tamu",
      "Akses 24 Jam",
      "Dilarang bawa hewan",
      "Maks. 1 orang/ kamar",
      "Kriteria umum"
    ],
    "landmarks": [
      {
        "nama": "Dkve Warmindo",
        "jarak": "1.9 km"
      },
      {
        "nama": "Bethel Full Gospel Church Kepunton",
        "jarak": "597 m"
      },
      {
        "nama": "Universitas Sebelas Maret",
        "jarak": "2.2 km"
      },
      {
        "nama": "RS Umum Hermina Solo",
        "jarak": "360 m"
      },
      {
        "nama": "Solo Paragon Mall",
        "jarak": "3.0 km"
      }
    ],
    "region": "solo-kota-surakarta-jawa-tengah-indonesia",
    "url": "https://mamikos.com/room/kost-kota-surakarta-kost-putri-eksklusif-kost-ndalem-mitrosuwarnan-tipe-a-jebres-surakarta?redirection_source=list%20kos%20result",
    "scraped_at": "2025-09-27T10:46:08.317725"
  },
  {
    "nama_kos": "Kost Anugrah Tipe A Banjarsari Surakarta",
    "jenis_kos": "Kos Putri",
    "area": "Banjarsari",
    "rating": "",
    "jumlah_review": "",
    "total_transaksi": "",
    "harga": "Rp925.000",
    "periode": "/bulan",
    "alamat": "Banjarsari, Kota Surakarta, Surakarta",
    "fasilitas": {
      "ukuran_listrik": [
        "3 x 3 meter",
        "Tidak termasuk listrik"
      ],
      "kamar": [
        "AC",
        "Kasur",
        "Meja",
        "Lemari / Storage",
        "Kursi"
      ],
      "kamar_mandi": [
        "K. Mandi Dalam",
        "Kloset Duduk",
        "Kloset Jongkok",
        "K. Mandi Luar",
        "Shower"
      ],
      "umum": [
        "WiFi",
        "R. Cuci",
        "Kulkas",
        "R. Tamu",
        "Penjaga Kos"
      ],
      "parkir": [
        "Parkir Motor",
        "Parkir Sepeda"
      ]
    },
    "peraturan": [
      "Tipe ini bisa diisi maks. 1 orang/ kamar",
      "Tidak untuk pasutri",
      "Tidak boleh bawa anak",
      "Deposit",
      "Ada jam malam",
      "Ada jam malam untuk tamu",
      "Dilarang menerima tamu"
    ],
    "landmarks": [
      {
        "nama": "Rumah Makan Pak Die Solo Balapan",
        "jarak": "257 m"
      },
      {
        "nama": "Gereja Bethany Solo",
        "jarak": "351 m"
      },
      {
        "nama": "Sekolah Tinggi Ilmu Ekonomi Adi Unggul Bhirawa",
        "jarak": "1.6 km"
      },
      {
        "nama": "RS Umum PKU Muhammadiyah Surakarta",
        "jarak": "952 m"
      },
      {
        "nama": "Solo Paragon Mall",
        "jarak": "1.5 km"
      }
    ],
    "region": "solo-kota-surakarta-jawa-tengah-indonesia",
    "url": "https://mamikos.com/room/kost-kota-surakarta-kost-putri-murah-kost-anugrah-tipe-a-banjarsari-surakarta?redirection_source=list%20kos%20result",
    "scraped_at": "2025-09-27T10:46:17.297931"
  },
  {
    "nama_kos": "Kost Gracia Tipe A Pasar Kliwon Surakarta",
    "jenis_kos": "Kos Putri",
    "area": "Pasar Kliwon",
    "rating": "",
    "jumlah_review": "",
    "total_transaksi": "",
    "harga": "Rp950.000",
    "periode": "/bulan",
    "alamat": "Pasar Kliwon, Kota Surakarta, Surakarta",
    "fasilitas": {
      "ukuran_listrik": [
        "3 x 3 meter",
        "Tidak termasuk listrik"
      ],
      "kamar": [
        "AC",
        "Kasur",
        "Lemari / Storage",
        "Ventilasi",
        "Jendela"
      ],
      "kamar_mandi": [
        "K. Mandi Dalam",
        "Kloset Duduk",
        "K. Mandi Luar",
        "Ember mandi",
        "Shower"
      ],
      "umum": [
        "WiFi",
        "Kulkas",
        "R. Cuci",
        "Mesin Cuci",
        "R. Tamu"
      ],
      "parkir": [
        "Parkir Motor",
        "Parkir Sepeda",
        "Parkir Motor & Sepeda"
      ]
    },
    "peraturan": [
      "Tipe ini bisa diisi maks. 2 orang/ kamar",
      "Tidak untuk pasutri",
      "Tidak boleh bawa anak",
      "Deposit",
      "Denda keterlambatan",
      "Ada jam malam",
      "Ada jam malam untuk tamu",
      "Denda kerusakan barang kos",
      "Dilarang bawa hewan",
      "Dilarang merokok di kamar"
    ],
    "landmarks": [
      {
        "nama": "Rumah Makan Kemuning",
        "jarak": "3.1 km"
      },
      {
        "nama": "Masjid Ar Riyadh Solo",
        "jarak": "1.2 km"
      },
      {
        "nama": "Bank Mandiri Solo Baru Raya",
        "jarak": "3.4 km"
      },
      {
        "nama": "Universitas Sebelas Maret",
        "jarak": "2.9 km"
      },
      {
        "nama": "RS PKU Muhammadiyah Sampangan Surakarta",
        "jarak": "957 m"
      },
      {
        "nama": "Solo Paragon Mall",
        "jarak": "2.9 km"
      }
    ],
    "region": "solo-kota-surakarta-jawa-tengah-indonesia",
    "url": "https://mamikos.com/room/kost-kota-surakarta-kost-putri-murah-kost-gracia-tipe-a-pasar-kliwon-surakarta-2?redirection_source=list%20kos%20result",
    "scraped_at": "2025-09-27T10:46:28.303381"
  },
  {
    "nama_kos": "Kost Kadirejo Jebres Surakarta",
    "jenis_kos": "Kos Campur",
    "area": "Kecamatan Jebres",
    "rating": "",
    "jumlah_review": "",
    "total_transaksi": "",
    "harga": "Rp650.000",
    "periode": "/bulan",
    "alamat": "Kecamatan Jebres, Kota Surakarta, Surakarta",
    "fasilitas": {
      "ukuran_listrik": [
        "3 x 4 meter",
        "Termasuk listrik"
      ],
      "kamar": [
        "Kasur",
        "Ventilasi",
        "Bantal",
        "Guling",
        "Jendela"
      ],
      "kamar_mandi": [
        "K. Mandi Dalam",
        "Kloset Duduk",
        "Ember mandi",
        "Shower"
      ],
      "umum": [
        "WiFi",
        "R. Jemur",
        "Dapur",
        "Balcon",
        "CCTV"
      ],
      "parkir": [
        "Parkir Motor",
        "Parkir Sepeda",
        "Parkir Motor & Sepeda"
      ]
    },
    "peraturan": [
      "Tamu menginap dikenakan biaya",
      "Tipe ini bisa diisi maks. 3 orang/ kamar",
      "Tidak untuk pasutri",
      "Boleh bawa anak",
      "Akses 24 Jam",
      "Boleh bawa anak",
      "Kriteria umum",
      "Maks. 3 orang/ kamar",
      "Tamu dilarang menginap"
    ],
    "landmarks": [
      {
        "nama": "Rumah Makan Pak Die Solo Balapan",
        "jarak": "2.5 km"
      },
      {
        "nama": "Bethel Full Gospel Church Kepunton",
        "jarak": "1.5 km"
      },
      {
        "nama": "Universitas Sebelas Maret",
        "jarak": "2.3 km"
      },
      {
        "nama": "RS PKU Muhammadiyah Sampangan Surakarta",
        "jarak": "1.1 km"
      }
    ],
    "region": "solo-kota-surakarta-jawa-tengah-indonesia",
    "url": "https://mamikos.com/room/kost-kota-surakarta-kost-campur-murah-kost-kadirejo-jebres-surakarta?redirection_source=list%20kos%20result",
    "scraped_at": "2025-09-27T10:46:39.865741"
  },
  {
    "nama_kos": "Kost Triyanto Tipe B Kwarasan Grogol Sukoharjo",
    "jenis_kos": "Kos Campur",
    "area": "Grogol",
    "rating": "",
    "jumlah_review": "",
    "total_transaksi": "4 transaksi berhasil di kos ini",
    "harga": "Rp800.000",
    "periode": "/bulan",
    "alamat": "Grogol, Kabupaten Sukoharjo, Sukoharjo",
    "fasilitas": {
      "ukuran_listrik": [
        "3 x 4 meter",
        "Termasuk listrik"
      ],
      "kamar": [
        "Kasur",
        "Meja",
        "Lemari / Storage",
        "Ventilasi",
        "Kursi"
      ],
      "kamar_mandi": [
        "K. Mandi Dalam",
        "Kloset Duduk",
        "R. Santai"
      ],
      "umum": [
        "WiFi",
        "R. Jemur",
        "Dapur",
        "Dispenser"
      ],
      "parkir": [
        "Parkir Motor"
      ]
    },
    "peraturan": [
      "Tipe ini bisa diisi maks. 1 orang/ kamar",
      "Tidak untuk pasutri",
      "Tidak boleh bawa anak",
      "Akses 24 Jam",
      "Khusus karyawan",
      "Maks. 1 orang/ kamar"
    ],
    "landmarks": [
      {
        "nama": "2Susu Cafe",
        "jarak": "2.7 km"
      },
      {
        "nama": "Gereja Katolik San Inigo, Dirjodipuran",
        "jarak": "1.7 km"
      },
      {
        "nama": "Bank Mandiri Solo Baru Raya",
        "jarak": "444 m"
      },
      {
        "nama": "Akademi Teknnologi Warga Surakarta",
        "jarak": "932 m"
      },
      {
        "nama": "RS Umum Indriati",
        "jarak": "2.0 km"
      },
      {
        "nama": "The Park Mall Solo Baru, Grogol",
        "jarak": "693 m"
      }
    ],
    "region": "solo-kota-surakarta-jawa-tengah-indonesia",
    "url": "https://mamikos.com/room/kost-kabupaten-sukoharjo-kost-campur-murah-kost-triyanto-tipe-b-kwarasan-grogol-sukoharjo-1?redirection_source=list%20kos%20result",
    "scraped_at": "2025-09-27T10:46:49.970632"
  },
  {
    "nama_kos": "Kost Exclusive Almeyra Tipe A dan B Grogol Sukoharjo",
    "jenis_kos": "Kos Putri",
    "area": "Grogol",
    "rating": "",
    "jumlah_review": "",
    "total_transaksi": "",
    "harga": "Rp1.200.000",
    "periode": "/bulan",
    "alamat": "Grogol, Kabupaten Sukoharjo, Sukoharjo",
    "fasilitas": {
      "ukuran_listrik": [
        "4 x 4 meter",
        "Tidak termasuk listrik"
      ],
      "kamar": [
        "AC",
        "Kasur",
        "Meja",
        "Meja Rias"
      ],
      "kamar_mandi": [
        "K. Mandi Dalam",
        "Kloset Duduk",
        "K. Mandi Luar",
        "Wastafel",
        "Ember mandi"
      ],
      "umum": [
        "Dispenser",
        "WiFi",
        "Kulkas",
        "R. Cuci",
        "Mesin Cuci",
        "Penjaga Kos"
      ],
      "parkir": [
        "Parkir Mobil",
        "Parkir Motor",
        "Parkir Sepeda"
      ]
    },
    "peraturan": [
      "Tamu boleh menginap",
      "Tipe ini bisa diisi maks. 3 orang/ kamar",
      "Tidak untuk pasutri",
      "Tidak boleh bawa anak",
      "Ada jam malam untuk tamu",
      "Akses 24 Jam",
      "Check-in pukul 14:00-21:00 (sewa harian)",
      "Check-out maks. pukul 12:00 (sewa harian)",
      "Kriteria umum"
    ],
    "landmarks": [
      {
        "nama": "Berseri Warmindo",
        "jarak": "2.3 km"
      },
      {
        "nama": "Gereja Katolik San Inigo, Dirjodipuran",
        "jarak": "1.2 km"
      },
      {
        "nama": "Bank Mandiri Solo Baru Raya",
        "jarak": "1.3 km"
      },
      {
        "nama": "Akademi Analis Kesehatan Nasional Surakarta",
        "jarak": "804 m"
      },
      {
        "nama": "RS Umum Tk IV Slamet Riyadi Surakarta",
        "jarak": "2.4 km"
      },
      {
        "nama": "The Park Mall Solo Baru, Grogol",
        "jarak": "1.5 km"
      }
    ],
    "region": "solo-kota-surakarta-jawa-tengah-indonesia",
    "url": "https://mamikos.com/room/kost-kabupaten-sukoharjo-kost-putri-eksklusif-kost-exclusive-almeyra-tipe-a-dan-b-grogol-sukoharjo-2?redirection_source=list%20kos%20result",
    "scraped_at": "2025-09-27T10:47:00.336045"
  },
  {
    "nama_kos": "Kost Az Zahra Mangkubumen Banjarsari Surakarta",
    "jenis_kos": "Kos Putra",
    "area": "Banjarsari",
    "rating": "",
    "jumlah_review": "",
    "total_transaksi": "",
    "harga": "Rp900.000",
    "periode": "/bulan",
    "alamat": "Banjarsari, Kota Surakarta, Surakarta",
    "fasilitas": {
      "ukuran_listrik": [
        "3 x 4 meter",
        "Termasuk listrik"
      ],
      "kamar": [
        "Kasur",
        "Meja",
        "Lemari / Storage",
        "Ventilasi",
        "Kursi"
      ],
      "kamar_mandi": [
        "K. Mandi Dalam",
        "Kloset Jongkok",
        "Ember mandi",
        "Shower",
        "Taman"
      ],
      "umum": [
        "R. Jemur",
        "Balcon"
      ],
      "parkir": [
        "Parkir Motor",
        "Parkir Sepeda"
      ]
    },
    "peraturan": [
      "Tipe ini bisa diisi maks. 1 orang/ kamar",
      "Tidak untuk pasutri",
      "Tidak boleh bawa anak",
      "Tambah biaya untuk alat elektronik",
      "Ada jam malam untuk tamu",
      "Akses 24 Jam",
      "Denda kerusakan barang kos",
      "Dilarang bawa hewan",
      "Dilarang merokok di kamar"
    ],
    "landmarks": [
      {
        "nama": "Warteg Bolodewe",
        "jarak": "450 m"
      },
      {
        "nama": "Gereja Kristen Jawa Manahan",
        "jarak": "368 m"
      },
      {
        "nama": "Universitas Tunas Pembangunan Surakarta (UTP)",
        "jarak": "1.0 km"
      },
      {
        "nama": "RS Gigi dan Mulut Soelastri",
        "jarak": "676 m"
      },
      {
        "nama": "Solo Paragon Mall",
        "jarak": "244 m"
      }
    ],
    "region": "solo-kota-surakarta-jawa-tengah-indonesia",
    "url": "https://mamikos.com/room/kost-kota-surakarta-kost-putra-murah-kost-az-zahra-mangkubumen-banjarsari-surakarta?redirection_source=list%20kos%20result",
    "scraped_at": "2025-09-27T10:47:12.108741"
  },
  {
    "nama_kos": "Kost Griya Tenera Syariah Jebres Surakarta",
    "jenis_kos": "Kos Campur",
    "area": "Jebres",
    "rating": "",
    "jumlah_review": "",
    "total_transaksi": "5 transaksi berhasil di kos ini",
    "harga": "Rp1.950.000",
    "periode": "/bulan",
    "alamat": "Jebres, Kota Surakarta, Surakarta",
    "fasilitas": {
      "ukuran_listrik": [
        "3 x 6 meter",
        "Termasuk listrik"
      ],
      "kamar": [
        "AC",
        "Kasur",
        "Meja",
        "TV",
        "Lemari / Storage"
      ],
      "kamar_mandi": [
        "K. Mandi Dalam",
        "Kloset Duduk",
        "Wastafel",
        "Ember mandi",
        "Shower"
      ],
      "umum": [
        "WiFi",
        "Penjaga Kos",
        "Laundry",
        "Mushola",
        "Dapur"
      ],
      "parkir": [
        "Parkir Mobil",
        "Parkir Motor",
        "Parkir Sepeda"
      ]
    },
    "peraturan": [
      "Tipe ini bisa diisi maks. 2 orang/ kamar",
      "Boleh pasutri",
      "Tidak boleh bawa anak",
      "Akses 24 Jam",
      "Boleh pasutri",
      "Denda kerusakan barang kos",
      "Dilarang bawa hewan",
      "Harga termasuk listrik (sewa harian)"
    ],
    "landmarks": [
      {
        "nama": "Dkve Warmindo",
        "jarak": "1.5 km"
      },
      {
        "nama": "Bethel Full Gospel Church Kepunton",
        "jarak": "204 m"
      },
      {
        "nama": "Universitas Sebelas Maret",
        "jarak": "2.5 km"
      },
      {
        "nama": "RS Umum Hermina Solo",
        "jarak": "744 m"
      },
      {
        "nama": "Solo Paragon Mall",
        "jarak": "2.7 km"
      }
    ],
    "region": "solo-kota-surakarta-jawa-tengah-indonesia",
    "url": "https://mamikos.com/room/kost-kota-surakarta-kost-campur-eksklusif-kost-griya-tenera-syariah-jebres-surakarta?redirection_source=list%20kos%20result",
    "scraped_at": "2025-09-27T10:47:21.860878"
  },
  {
    "nama_kos": "Kost Grenmami Tipe A Jebres Surakarta",
    "jenis_kos": "Kos Putri",
    "area": "Jebres",
    "rating": "",
    "jumlah_review": "",
    "total_transaksi": "3 transaksi berhasil di kos ini",
    "harga": "Rp1.300.000",
    "periode": "/bulan",
    "alamat": "Jebres, Kota Surakarta, Surakarta",
    "fasilitas": {
      "ukuran_listrik": [
        "3 x 4 meter",
        "Tidak termasuk listrik"
      ],
      "kamar": [
        "AC",
        "Kasur",
        "Meja",
        "Lemari / Storage",
        "Ventilasi"
      ],
      "kamar_mandi": [
        "K. Mandi Dalam",
        "Kloset Duduk",
        "Kloset Jongkok",
        "K. Mandi Luar",
        "Ember mandi"
      ],
      "umum": [
        "WiFi",
        "Kulkas",
        "R. Cuci",
        "Penjaga Kos",
        "R. Tamu"
      ],
      "parkir": [
        "Parkir Motor & Sepeda"
      ]
    },
    "peraturan": [
      "Tipe ini bisa diisi maks. 1 orang/ kamar",
      "Tidak untuk pasutri",
      "Tidak boleh bawa anak",
      "Ada jam malam",
      "Ada jam malam untuk tamu",
      "Akses 24 Jam",
      "Denda kerusakan barang kos",
      "Dilarang merokok di kamar"
    ],
    "landmarks": [
      {
        "nama": "Warteg Alaska",
        "jarak": "1.8 km"
      },
      {
        "nama": "Bethel Full Gospel Church Kepunton",
        "jarak": "1.1 km"
      },
      {
        "nama": "Universitas Sebelas Maret",
        "jarak": "1.6 km"
      },
      {
        "nama": "RS Umum Hermina Solo",
        "jarak": "205 m"
      }
    ],
    "region": "solo-kota-surakarta-jawa-tengah-indonesia",
    "url": "https://mamikos.com/room/kost-kota-surakarta-kost-putri-eksklusif-kost-grenmami-tipe-a-jebres-surakarta-2?redirection_source=list%20kos%20result",
    "scraped_at": "2025-09-27T10:47:32.989862"
  },
  {
    "nama_kos": "Kost Triyanto II Tipe C Serengan Surakarta",
    "jenis_kos": "Kos Campur",
    "area": "Serengan",
    "rating": "",
    "jumlah_review": "",
    "total_transaksi": "1 transaksi berhasil di kos ini",
    "harga": "Rp1.200.000",
    "periode": "/bulan",
    "alamat": "Serengan, Kota Surakarta, Surakarta",
    "fasilitas": {
      "ukuran_listrik": [
        "3 x 4 meter",
        "Termasuk listrik"
      ],
      "kamar": [
        "AC",
        "Kasur",
        "Meja",
        "Lemari / Storage",
        "Ventilasi"
      ],
      "kamar_mandi": [
        "K. Mandi Dalam",
        "Kloset Duduk",
        "Ember mandi",
        "Shower"
      ],
      "umum": [
        "WiFi",
        "R. Cuci",
        "R. Tamu",
        "R. Jemur",
        "Dapur"
      ],
      "parkir": [
        "Parkir Motor",
        "Parkir Sepeda"
      ]
    },
    "peraturan": [
      "Tipe ini bisa diisi maks. 1 orang/ kamar",
      "Tidak untuk pasutri",
      "Tidak boleh bawa anak",
      "Khusus karyawan"
    ],
    "landmarks": [
      {
        "nama": "Berseri Warmindo",
        "jarak": "2.3 km"
      },
      {
        "nama": "Gereja Katolik San Inigo, Dirjodipuran",
        "jarak": "731 m"
      },
      {
        "nama": "Akademi Analis Kesehatan Nasional Surakarta",
        "jarak": "279 m"
      },
      {
        "nama": "The Park Mall Solo Baru, Grogol",
        "jarak": "1.4 km"
      }
    ],
    "region": "solo-kota-surakarta-jawa-tengah-indonesia",
    "url": "https://mamikos.com/room/kost-kota-surakarta-kost-campur-eksklusif-kost-triyanto-ii-tipe-c-serengan-surakarta-1?redirection_source=list%20kos%20result",
    "scraped_at": "2025-09-27T10:47:43.436785"
  },
  {
    "nama_kos": "Kost Triyanto II Tipe B Serengan Surakarta",
    "jenis_kos": "Kos Campur",
    "area": "Serengan",
    "rating": "5.0",
    "jumlah_review": "(1)",
    "total_transaksi": "6 transaksi berhasil di kos ini",
    "harga": "Rp800.000",
    "periode": "/bulan",
    "alamat": "Serengan, Kota Surakarta, Surakarta",
    "fasilitas": {
      "ukuran_listrik": [
        "3 x 4 meter",
        "Termasuk listrik"
      ],
      "kamar": [
        "Kasur",
        "Meja",
        "Lemari / Storage",
        "Ventilasi",
        "Kursi"
      ],
      "kamar_mandi": [
        "K. Mandi Dalam",
        "Kloset Duduk",
        "Ember mandi",
        "Shower"
      ],
      "umum": [
        "WiFi",
        "R. Cuci",
        "R. Tamu",
        "R. Jemur",
        "Dapur"
      ],
      "parkir": [
        "Parkir Motor",
        "Parkir Sepeda"
      ]
    },
    "peraturan": [
      "Tipe ini bisa diisi maks. 1 orang/ kamar",
      "Tidak untuk pasutri",
      "Tidak boleh bawa anak",
      "Kriteria umum",
      "Maks. 1 orang/ kamar"
    ],
    "landmarks": [
      {
        "nama": "Berseri Warmindo",
        "jarak": "2.3 km"
      },
      {
        "nama": "Gereja Katolik San Inigo, Dirjodipuran",
        "jarak": "731 m"
      },
      {
        "nama": "Akademi Analis Kesehatan Nasional Surakarta",
        "jarak": "279 m"
      },
      {
        "nama": "The Park Mall Solo Baru, Grogol",
        "jarak": "1.4 km"
      }
    ],
    "region": "solo-kota-surakarta-jawa-tengah-indonesia",
    "url": "https://mamikos.com/room/kost-kota-surakarta-kost-campur-murah-kost-triyanto-ii-tipe-b-serengan-surakarta?redirection_source=list%20kos%20result",
    "scraped_at": "2025-09-27T10:47:53.657908"
  },
  {
    "nama_kos": "Kost Triyanto Tipe C Grogol Sukoharjo",
    "jenis_kos": "Kos Putri",
    "area": "Grogol",
    "rating": "5.0",
    "jumlah_review": "(1)",
    "total_transaksi": "1 transaksi berhasil di kos ini",
    "harga": "Rp600.000",
    "periode": "/bulan",
    "alamat": "Grogol, Kabupaten Sukoharjo, Sukoharjo",
    "fasilitas": {
      "ukuran_listrik": [
        "3 x 4 meter",
        "Termasuk listrik"
      ],
      "kamar": [
        "Kasur",
        "Meja",
        "Lemari / Storage",
        "Kursi"
      ],
      "kamar_mandi": [
        "K. Mandi Luar",
        "Gazebo"
      ],
      "umum": [],
      "parkir": [
        "Parkir Motor",
        "Parkir Sepeda"
      ]
    },
    "peraturan": [
      "Tipe ini bisa diisi maks. 1 orang/ kamar",
      "Tidak untuk pasutri",
      "Tidak boleh bawa anak",
      "Ada jam malam untuk tamu",
      "Dilarang bawa hewan",
      "Dilarang merokok di kamar",
      "Kamar hanya bagi penyewa",
      "Khusus Mahasiswa"
    ],
    "landmarks": [
      {
        "nama": "2Susu Cafe",
        "jarak": "2.7 km"
      },
      {
        "nama": "Gereja Katolik San Inigo, Dirjodipuran",
        "jarak": "1.7 km"
      },
      {
        "nama": "Bank Mandiri Solo Baru Raya",
        "jarak": "444 m"
      },
      {
        "nama": "Akademi Teknnologi Warga Surakarta",
        "jarak": "932 m"
      },
      {
        "nama": "RS Umum Indriati",
        "jarak": "2.0 km"
      },
      {
        "nama": "The Park Mall Solo Baru, Grogol",
        "jarak": "693 m"
      }
    ],
    "region": "solo-kota-surakarta-jawa-tengah-indonesia",
    "url": "https://mamikos.com/room/kost-kabupaten-sukoharjo-kost-campur-murah-kost-triyanto-tipe-c-grogol-sukoharjo?redirection_source=list%20kos%20result",
    "scraped_at": "2025-09-27T10:48:04.019108"
  },
  {
    "nama_kos": "Kost Yudi Pasar Kliwon Surakarta",
    "jenis_kos": "Kos Campur",
    "area": "Pasar Kliwon",
    "rating": "5.0",
    "jumlah_review": "(1)",
    "total_transaksi": "9 transaksi berhasil di kos ini",
    "harga": "Rp700.000",
    "periode": "/bulan",
    "alamat": "Pasar Kliwon, Kota Surakarta, Surakarta",
    "fasilitas": {
      "ukuran_listrik": [
        "4 x 4 meter",
        "Tidak termasuk listrik"
      ],
      "kamar": [
        "Kasur",
        "Lemari / Storage",
        "Jendela",
        "Kipas Angin"
      ],
      "kamar_mandi": [
        "K. Mandi Dalam",
        "Kloset Jongkok"
      ],
      "umum": [
        "WiFi"
      ],
      "parkir": [
        "Parkir Motor & Sepeda"
      ]
    },
    "peraturan": [
      "Tamu boleh menginap",
      "Tipe ini bisa diisi maks. 3 orang/ kamar",
      "Boleh pasutri",
      "Boleh bawa anak",
      "Denda keterlambatan",
      "Akses 24 Jam",
      "Tamu bebas berkunjung",
      "Tamu boleh menginap",
      "Boleh pasutri",
      "Boleh bawa anak"
    ],
    "landmarks": [
      {
        "nama": "Berseri Warmindo",
        "jarak": "3.0 km"
      },
      {
        "nama": "Masjid Ar Riyadh Solo",
        "jarak": "519 m"
      },
      {
        "nama": "BCA KCU Solo Baru",
        "jarak": "1.9 km"
      },
      {
        "nama": "Akademi Analis Kesehatan Nasional Surakarta",
        "jarak": "1.2 km"
      },
      {
        "nama": "RSUP Surakarta",
        "jarak": "674 m"
      },
      {
        "nama": "The Park Mall Solo Baru, Grogol",
        "jarak": "1.9 km"
      }
    ],
    "region": "solo-kota-surakarta-jawa-tengah-indonesia",
    "url": "https://mamikos.com/room/kost-kota-surakarta-kost-campur-eksklusif-kost-yudi-pasar-kliwon-surakarta?redirection_source=list%20kos%20result",
    "scraped_at": "2025-09-27T10:48:12.103563"
  },
  {
    "nama_kos": "Kost Cokrosuman Tipe A Serengan Surakarta",
    "jenis_kos": "Kos Putri",
    "area": "Serengan",
    "rating": "",
    "jumlah_review": "",
    "total_transaksi": "",
    "harga": "Rp650.000",
    "periode": "/bulan",
    "alamat": "Serengan, Kota Surakarta, Surakarta",
    "fasilitas": {
      "ukuran_listrik": [
        "2.5 x 5 meter",
        "Tidak termasuk listrik"
      ],
      "kamar": [
        "Kasur",
        "Ventilasi",
        "Jendela"
      ],
      "kamar_mandi": [
        "K. Mandi Dalam",
        "Kloset Duduk",
        "Ember mandi",
        "Shower",
        "R. Santai"
      ],
      "umum": [
        "WiFi",
        "Penjaga Kos",
        "R. Tamu",
        "Dapur"
      ],
      "parkir": [
        "Parkir Motor"
      ]
    },
    "peraturan": [
      "> 5 orang/ kamar",
      "Tidak untuk pasutri",
      "Tidak boleh bawa anak",
      "> 5 orang/ kamar",
      "Ada jam malam",
      "Ada jam malam untuk tamu",
      "Dilarang bawa hewan",
      "Dilarang merokok di kamar"
    ],
    "landmarks": [
      {
        "nama": "Berseri Warmindo",
        "jarak": "755 m"
      },
      {
        "nama": "Masjid Al Wustho Mangkunegaran",
        "jarak": "792 m"
      },
      {
        "nama": "Bank Mandiri Solo Baru Raya",
        "jarak": "2.9 km"
      },
      {
        "nama": "Universitas Tunas Pembangunan Surakarta (UTP)",
        "jarak": "2.3 km"
      },
      {
        "nama": "RSUP Surakarta",
        "jarak": "2.9 km"
      },
      {
        "nama": "Solo Paragon Mall",
        "jarak": "1.3 km"
      }
    ],
    "region": "solo-kota-surakarta-jawa-tengah-indonesia",
    "url": "https://mamikos.com/room/kost-kota-surakarta-kost-putri-murah-kost-cokrosuman-tipe-a-serengan-surakarta?redirection_source=list%20kos%20result",
    "scraped_at": "2025-09-27T10:48:21.666634"
  },
  {
    "nama_kos": "Kost Miracle Serengan Surakarta",
    "jenis_kos": "Kos Campur",
    "area": "Serengan",
    "rating": "",
    "jumlah_review": "",
    "total_transaksi": "1 transaksi berhasil di kos ini",
    "harga": "Rp450.000",
    "periode": "/bulan",
    "alamat": "Serengan, Kota Surakarta, Surakarta",
    "fasilitas": {
      "ukuran_listrik": [
        "3.7 x 3.5 meter",
        "Termasuk listrik"
      ],
      "kamar": [
        "Kasur",
        "Lemari / Storage",
        "Bantal"
      ],
      "kamar_mandi": [
        "Kloset Jongkok",
        "K. Mandi Luar",
        "Ember mandi"
      ],
      "umum": [
        "WiFi",
        "R. Cuci",
        "R. Tamu",
        "Mesin Cuci",
        "Penjaga Kos"
      ],
      "parkir": [
        "Parkir Motor",
        "Parkir Sepeda"
      ]
    },
    "peraturan": [
      "Tipe ini bisa diisi maks. 1 orang/ kamar",
      "Tidak untuk pasutri",
      "Tidak boleh bawa anak",
      "Tambah biaya untuk alat elektronik",
      "Denda kerusakan barang kos",
      "Dilarang bawa hewan",
      "Harga termasuk listrik (sewa harian)",
      "Kamar hanya bagi penyewa",
      "Lawan jenis dilarang ke kamar"
    ],
    "landmarks": [
      {
        "nama": "Berseri Warmindo",
        "jarak": "3.4 km"
      },
      {
        "nama": "Gereja Katolik San Inigo, Dirjodipuran",
        "jarak": "1.4 km"
      },
      {
        "nama": "The Park Mall Solo Baru, Grogol",
        "jarak": "1.2 km"
      }
    ],
    "region": "solo-kota-surakarta-jawa-tengah-indonesia",
    "url": "https://mamikos.com/room/kost-kota-surakarta-kost-campur-murah-kost-miracle-serengan-surakarta-4?redirection_source=list%20kos%20result",
    "scraped_at": "2025-09-27T10:48:31.606406"
  },
  {
    "nama_kos": "Kost Grenmami Tipe B Jebres Surakarta",
    "jenis_kos": "Kos Putri",
    "area": "Kecamatan Jebres",
    "rating": "",
    "jumlah_review": "",
    "total_transaksi": "1 transaksi berhasil di kos ini",
    "harga": "Rp1.600.000",
    "periode": "/bulan",
    "alamat": "Kecamatan Jebres, Kota Surakarta, Surakarta",
    "fasilitas": {
      "ukuran_listrik": [
        "3 x 3 meter",
        "Tidak termasuk listrik"
      ],
      "kamar": [
        "AC",
        "Kasur",
        "Meja",
        "TV",
        "Lemari / Storage"
      ],
      "kamar_mandi": [
        "K. Mandi Dalam",
        "Kloset Duduk",
        "Ember mandi",
        "Wastafel",
        "Shower"
      ],
      "umum": [
        "WiFi",
        "Kulkas",
        "R. Cuci",
        "Mesin Cuci",
        "Penjaga Kos"
      ],
      "parkir": []
    },
    "peraturan": [
      "Tipe ini bisa diisi maks. 1 orang/ kamar",
      "Tidak untuk pasutri",
      "Tidak boleh bawa anak",
      "Ada jam malam untuk tamu",
      "Akses 24 Jam",
      "Tidak untuk pasutri",
      "Denda kerusakan barang kos",
      "Dilarang merokok di kamar"
    ],
    "landmarks": [
      {
        "nama": "Warteg Alaska",
        "jarak": "1.8 km"
      },
      {
        "nama": "Bethel Full Gospel Church Kepunton",
        "jarak": "1.1 km"
      },
      {
        "nama": "Universitas Sebelas Maret",
        "jarak": "1.6 km"
      },
      {
        "nama": "RS Umum Hermina Solo",
        "jarak": "206 m"
      }
    ],
    "region": "solo-kota-surakarta-jawa-tengah-indonesia",
    "url": "https://mamikos.com/room/kost-kota-surakarta-kost-putri-eksklusif-kost-grenmami-tipe-b-jebres-surakarta?redirection_source=list%20kos%20result",
    "scraped_at": "2025-09-27T10:48:41.984301"
  },
  {
    "nama_kos": "Kost De Orange Tipe C Banjarsari Surakarta",
    "jenis_kos": "Kos Putra",
    "area": "Banjarsari",
    "rating": "",
    "jumlah_review": "",
    "total_transaksi": "1 transaksi berhasil di kos ini",
    "harga": "Rp1.350.000",
    "periode": "/bulan",
    "alamat": "Banjarsari, Kota Surakarta, Surakarta",
    "fasilitas": {
      "ukuran_listrik": [
        "3 x 4 meter",
        "Tidak termasuk listrik"
      ],
      "kamar": [
        "AC",
        "Kasur",
        "Meja",
        "Bantal",
        "Kursi"
      ],
      "kamar_mandi": [
        "K. Mandi Dalam",
        "Kloset Jongkok",
        "Shower"
      ],
      "umum": [
        "WiFi"
      ],
      "parkir": [
        "Parkir Motor"
      ]
    },
    "peraturan": [
      "Tipe ini bisa diisi maks. 1 orang/ kamar",
      "Tidak untuk pasutri",
      "Tidak boleh bawa anak",
      "Ada jam malam",
      "Ada jam malam untuk tamu",
      "Akses 24 Jam",
      "Dilarang bawa hewan",
      "Lawan jenis dilarang ke kamar"
    ],
    "landmarks": [
      {
        "nama": "Warteg Bolodewe",
        "jarak": "359 m"
      },
      {
        "nama": "Gereja Kristen Jawa Manahan",
        "jarak": "277 m"
      },
      {
        "nama": "Universitas Tunas Pembangunan Surakarta (UTP)",
        "jarak": "921 m"
      },
      {
        "nama": "RS Gigi dan Mulut Soelastri",
        "jarak": "755 m"
      },
      {
        "nama": "Solo Paragon Mall",
        "jarak": "335 m"
      }
    ],
    "region": "solo-kota-surakarta-jawa-tengah-indonesia",
    "url": "https://mamikos.com/room/kost-kota-surakarta-kost-putra-eksklusif-kost-de-orange-tipe-c-banjarsari-surakarta?redirection_source=list%20kos%20result",
    "scraped_at": "2025-09-27T10:48:51.356840"
  },
  {
    "nama_kos": "Kost Triyanto Tipe D Grogol Sukoharjo",
    "jenis_kos": "Kos Campur",
    "area": "Grogol",
    "rating": "",
    "jumlah_review": "",
    "total_transaksi": "1 transaksi berhasil di kos ini",
    "harga": "Rp1.200.000",
    "periode": "/bulan",
    "alamat": "Grogol, Kabupaten Sukoharjo, Sukoharjo",
    "fasilitas": {
      "ukuran_listrik": [
        "3 x 4 meter",
        "Termasuk listrik"
      ],
      "kamar": [
        "AC",
        "Kasur",
        "Meja",
        "TV",
        "Lemari / Storage"
      ],
      "kamar_mandi": [
        "K. Mandi Dalam",
        "Kloset Duduk",
        "Ember mandi",
        "Wastafel",
        "Shower",
        "Taman",
        "Gazebo"
      ],
      "umum": [
        "WiFi",
        "R. Jemur",
        "Balcon"
      ],
      "parkir": [
        "Parkir Mobil",
        "Parkir Motor",
        "Parkir Sepeda"
      ]
    },
    "peraturan": [
      "Tipe ini bisa diisi maks. 2 orang/ kamar",
      "Tidak untuk pasutri",
      "Tidak boleh bawa anak",
      "Akses 24 Jam",
      "Kriteria umum",
      "Maks. 2 orang/ kamar"
    ],
    "landmarks": [
      {
        "nama": "2Susu Cafe",
        "jarak": "2.7 km"
      },
      {
        "nama": "Gereja Katolik San Inigo, Dirjodipuran",
        "jarak": "1.7 km"
      },
      {
        "nama": "Bank Mandiri Solo Baru Raya",
        "jarak": "444 m"
      },
      {
        "nama": "Akademi Teknnologi Warga Surakarta",
        "jarak": "932 m"
      },
      {
        "nama": "RS Umum Indriati",
        "jarak": "2.0 km"
      },
      {
        "nama": "The Park Mall Solo Baru, Grogol",
        "jarak": "693 m"
      }
    ],
    "region": "solo-kota-surakarta-jawa-tengah-indonesia",
    "url": "https://mamikos.com/room/kost-kabupaten-sukoharjo-kost-campur-eksklusif-kost-triyanto-tipe-d-grogol-sukoharjo?redirection_source=list%20kos%20result",
    "scraped_at": "2025-09-27T10:49:02.335685"
  },
  {
    "nama_kos": "Kost Ndalem Tentrem Tipe Standar Serengan Surakarta",
    "jenis_kos": "Kos Putra",
    "area": "Kecamatan Serengan",
    "rating": "",
    "jumlah_review": "",
    "total_transaksi": "",
    "harga": "Rp650.000",
    "periode": "/bulan",
    "alamat": "Kecamatan Serengan, Kota Surakarta, Surakarta",
    "fasilitas": {
      "ukuran_listrik": [
        "3 x 3 meter",
        "Termasuk listrik"
      ],
      "kamar": [
        "Kasur",
        "Meja",
        "Lemari / Storage",
        "Ventilasi",
        "Jendela"
      ],
      "kamar_mandi": [
        "K. Mandi Dalam",
        "Kloset Duduk",
        "Kloset Jongkok",
        "K. Mandi Luar",
        "Ember mandi"
      ],
      "umum": [
        "WiFi",
        "Kulkas",
        "R. Cuci",
        "R. Tamu",
        "R. Jemur"
      ],
      "parkir": [
        "Parkir Mobil",
        "Parkir Motor",
        "Parkir Sepeda",
        "Parkir Motor & Sepeda"
      ]
    },
    "peraturan": [
      "Tamu menginap dikenakan biaya",
      "Tipe ini bisa diisi maks. 1 orang/ kamar",
      "Tidak untuk pasutri",
      "Tidak boleh bawa anak",
      "Tambah biaya untuk alat elektronik",
      "Ada jam malam untuk tamu",
      "Akses 24 Jam",
      "Denda kerusakan barang kos",
      "Dilarang bawa hewan",
      "Dilarang merokok di kamar"
    ],
    "landmarks": [
      {
        "nama": "Rumah Makan Pak Die Solo Balapan",
        "jarak": "2.8 km"
      },
      {
        "nama": "Masjid Al - Mukmin Surakarta",
        "jarak": "778 m"
      },
      {
        "nama": "Bank Mandiri Solo Baru Raya",
        "jarak": "1.7 km"
      },
      {
        "nama": "Akademi Analis Kesehatan Nasional Surakarta",
        "jarak": "374 m"
      },
      {
        "nama": "RSUP Surakarta",
        "jarak": "1.8 km"
      },
      {
        "nama": "The Park Mall Solo Baru, Grogol",
        "jarak": "1.8 km"
      }
    ],
    "region": "solo-kota-surakarta-jawa-tengah-indonesia",
    "url": "https://mamikos.com/room/kost-kota-surakarta-kost-putra-murah-kost-ndalem-tentrem-tipe-standar-serengan-surakarta-2?redirection_source=list%20kos%20result",
    "scraped_at": "2025-09-27T10:49:11.960696"
  },
  {
    "nama_kos": "Kost Kanaka Executive Serengan Surakarta",
    "jenis_kos": "Kos Putri",
    "area": "Kecamatan Serengan",
    "rating": "",
    "jumlah_review": "",
    "total_transaksi": "",
    "harga": "Rp1.600.000",
    "periode": "/bulan",
    "alamat": "Kecamatan Serengan, Kota Surakarta, Surakarta",
    "fasilitas": {
      "ukuran_listrik": [
        "3 x 4 meter",
        "Tidak termasuk listrik"
      ],
      "kamar": [
        "AC",
        "Kasur",
        "Meja",
        "Lemari / Storage",
        "Bantal"
      ],
      "kamar_mandi": [
        "K. Mandi Dalam",
        "Kloset Duduk",
        "Ember mandi",
        "Shower",
        "R. Santai"
      ],
      "umum": [
        "WiFi",
        "Kulkas",
        "Penjaga Kos",
        "Dapur"
      ],
      "parkir": [
        "Parkir Mobil",
        "Parkir Motor",
        "Parkir Sepeda",
        "Parkir Motor & Sepeda"
      ]
    },
    "peraturan": [
      "Tipe ini bisa diisi maks. 1 orang/ kamar",
      "Tidak untuk pasutri",
      "Tidak boleh bawa anak",
      "Ada jam malam",
      "Ada jam malam untuk tamu",
      "Denda kerusakan barang kos",
      "Dilarang merokok di kamar",
      "Kamar hanya bagi penyewa"
    ],
    "landmarks": [
      {
        "nama": "Warteg Bolodewe",
        "jarak": "2.6 km"
      },
      {
        "nama": "Gereja GUPDI KWARASAN",
        "jarak": "1.5 km"
      },
      {
        "nama": "Bank Mandiri Solo Baru Raya",
        "jarak": "2.0 km"
      },
      {
        "nama": "Universitas Tunas Pembangunan Surakarta (UTP)",
        "jarak": "3.1 km"
      },
      {
        "nama": "RS PKU Muhammadiyah Sampangan Surakarta",
        "jarak": "2.7 km"
      },
      {
        "nama": "Solo Paragon Mall",
        "jarak": "1.9 km"
      }
    ],
    "region": "solo-kota-surakarta-jawa-tengah-indonesia",
    "url": "https://mamikos.com/room/kost-kota-surakarta-kost-putri-eksklusif-kost-kanaka-executive-serengan-surakarta-2?redirection_source=list%20kos%20result",
    "scraped_at": "2025-09-27T10:49:21.324959"
  }
]